{"openapi":"3.0.0","paths":{"/addpackage":{"post":{"summary":"Adds a new package to a product by an admin user.","tags":["package"],"operationId":"Adds_a new package to a product by an admin user.","requestBody":{"type":"object","required":["productId","name","userId"],"properties":{"productId":{"type":"string"},"name":{"type":"string"},"userId":{"type":"string"}}},"responses":{"200":{"description":"Package created successfully","content":{"application/json":{"schema":{"type":"object","properties":{"message":{"type":"string"},"package":{"type":"object"}}}}}}}}},"/addproduct":{"post":{"summary":"Adds a new product to a company by an admin user.","tags":["product"],"operationId":"Adds_a new product to a company by an admin user.","requestBody":{"type":"object","required":["companyId","name","userId"],"properties":{"companyId":{"type":"string"},"name":{"type":"string"},"description":{"type":"string"},"userId":{"type":"string"}}},"responses":{"200":{"description":"Product created successfully","content":{"application/json":{"schema":{"type":"object","properties":{"message":{"type":"string"},"product":{"type":"object"}}}}}}}}},"/addsubscription":{"post":{"summary":"Adds a new subscription for a user by an admin.","tags":["subscription"],"operationId":"Adds_a new subscription for a user by an admin.","requestBody":{"type":"object","required":["userId","packageId","targetUserId"],"properties":{"userId":{"type":"string"},"packageId":{"type":"string"},"targetUserId":{"type":"string"}}},"responses":{"200":{"description":"Subscription created successfully","content":{"application/json":{"schema":{"type":"object","properties":{"message":{"type":"string"},"subscription":{"type":"object"}}}}}}}}},"/verify/user":{"get":{"summary":"Greet the authenticated user","tags":["helloworld"],"operationId":"Greet_the authenticated user","responses":{"200":{"description":"Successful response","content":{"application/json":{"schema":{"type":"object","properties":{"message":{"type":"string"}}}}}}}}},"/schema/company":{"post":{"summary":"Create a new Company","description":"Create Company from database","tags":["schema.company.create"],"operationId":"Create_a new Company","requestBody":{"content":{"application/json":{"schema":{"$ref":"#/components/schemas/schema_Company"}}}},"responses":{"201":{"content":{"application/json":{"schema":{"type":"object"}}}}}}},"/schema/company/{id}":{"delete":{"summary":"Delete a Company","description":"Delete Company from database","tags":["schema.company.delete"],"operationId":"Delete_a Company","parameters":[{"name":"id","in":"path","required":true,"schema":{"type":"string"}}],"responses":{"202":{"content":{"application/json":{"schema":{"type":"object"}}}}}},"get":{"summary":"Fetch Company","description":"Fetch Company from database","tags":["schema.company.one"],"operationId":"Fetch_Company","parameters":[{"name":"id","in":"path","required":true,"schema":{"type":"string"}}],"responses":{"200":{"content":{"application/json":{"schema":{"type":"object"}}}}}},"put":{"summary":"Update a Company","description":"Update Company from database","tags":["schema.company.update"],"operationId":"Update_a Company","requestBody":{"content":{"application/json":{"schema":{"$ref":"#/components/schemas/schema_Company"}}}},"parameters":[{"name":"id","in":"path","required":true,"schema":{"type":"string"}}],"responses":{"204":{"content":{"application/json":{"schema":{"type":"object"}}}}}}},"/schema/company/search":{"post":{"summary":"Fetch multiple Company","description":"Fetch multiple Company from database","tags":["schema.company.search"],"operationId":"Fetch_multiple Company","requestBody":{"content":{"application/json":{"schema":{"type":"object"}}}},"responses":{"200":{"content":{"application/json":{"schema":{"type":"array"}}}}}}},"/schema/package":{"post":{"summary":"Create a new Package","description":"Create Package from database","tags":["schema.package.create"],"operationId":"Create_a new Package","requestBody":{"content":{"application/json":{"schema":{"$ref":"#/components/schemas/schema_Package"}}}},"responses":{"201":{"content":{"application/json":{"schema":{"type":"object"}}}}}}},"/schema/package/{id}":{"delete":{"summary":"Delete a Package","description":"Delete Package from database","tags":["schema.package.delete"],"operationId":"Delete_a Package","parameters":[{"name":"id","in":"path","required":true,"schema":{"type":"string"}}],"responses":{"202":{"content":{"application/json":{"schema":{"type":"object"}}}}}},"get":{"summary":"Fetch Package","description":"Fetch Package from database","tags":["schema.package.one"],"operationId":"Fetch_Package","parameters":[{"name":"id","in":"path","required":true,"schema":{"type":"string"}}],"responses":{"200":{"content":{"application/json":{"schema":{"type":"object"}}}}}},"put":{"summary":"Update a Package","description":"Update Package from database","tags":["schema.package.update"],"operationId":"Update_a Package","requestBody":{"content":{"application/json":{"schema":{"$ref":"#/components/schemas/schema_Package"}}}},"parameters":[{"name":"id","in":"path","required":true,"schema":{"type":"string"}}],"responses":{"204":{"content":{"application/json":{"schema":{"type":"object"}}}}}}},"/schema/package/search":{"post":{"summary":"Fetch multiple Package","description":"Fetch multiple Package from database","tags":["schema.package.search"],"operationId":"Fetch_multiple Package","requestBody":{"content":{"application/json":{"schema":{"type":"object"}}}},"responses":{"200":{"content":{"application/json":{"schema":{"type":"array"}}}}}}},"/schema/product":{"post":{"summary":"Create a new Product","description":"Create Product from database","tags":["schema.product.create"],"operationId":"Create_a new Product","requestBody":{"content":{"application/json":{"schema":{"$ref":"#/components/schemas/schema_Product"}}}},"responses":{"201":{"content":{"application/json":{"schema":{"type":"object"}}}}}}},"/schema/product/{id}":{"delete":{"summary":"Delete a Product","description":"Delete Product from database","tags":["schema.product.delete"],"operationId":"Delete_a Product","parameters":[{"name":"id","in":"path","required":true,"schema":{"type":"string"}}],"responses":{"202":{"content":{"application/json":{"schema":{"type":"object"}}}}}},"get":{"summary":"Fetch Product","description":"Fetch Product from database","tags":["schema.product.one"],"operationId":"Fetch_Product","parameters":[{"name":"id","in":"path","required":true,"schema":{"type":"string"}}],"responses":{"200":{"content":{"application/json":{"schema":{"type":"object"}}}}}},"put":{"summary":"Update a Product","description":"Update Product from database","tags":["schema.product.update"],"operationId":"Update_a Product","requestBody":{"content":{"application/json":{"schema":{"$ref":"#/components/schemas/schema_Product"}}}},"parameters":[{"name":"id","in":"path","required":true,"schema":{"type":"string"}}],"responses":{"204":{"content":{"application/json":{"schema":{"type":"object"}}}}}}},"/schema/product/search":{"post":{"summary":"Fetch multiple Product","description":"Fetch multiple Product from database","tags":["schema.product.search"],"operationId":"Fetch_multiple Product","requestBody":{"content":{"application/json":{"schema":{"type":"object"}}}},"responses":{"200":{"content":{"application/json":{"schema":{"type":"array"}}}}}}},"/schema/subscription":{"post":{"summary":"Create a new Subscription","description":"Create Subscription from database","tags":["schema.subscription.create"],"operationId":"Create_a new Subscription","requestBody":{"content":{"application/json":{"schema":{"$ref":"#/components/schemas/schema_Subscription"}}}},"responses":{"201":{"content":{"application/json":{"schema":{"type":"object"}}}}}}},"/schema/subscription/{id}":{"delete":{"summary":"Delete a Subscription","description":"Delete Subscription from database","tags":["schema.subscription.delete"],"operationId":"Delete_a Subscription","parameters":[{"name":"id","in":"path","required":true,"schema":{"type":"string"}}],"responses":{"202":{"content":{"application/json":{"schema":{"type":"object"}}}}}},"get":{"summary":"Fetch Subscription","description":"Fetch Subscription from database","tags":["schema.subscription.one"],"operationId":"Fetch_Subscription","parameters":[{"name":"id","in":"path","required":true,"schema":{"type":"string"}}],"responses":{"200":{"content":{"application/json":{"schema":{"type":"object"}}}}}},"put":{"summary":"Update a Subscription","description":"Update Subscription from database","tags":["schema.subscription.update"],"operationId":"Update_a Subscription","requestBody":{"content":{"application/json":{"schema":{"$ref":"#/components/schemas/schema_Subscription"}}}},"parameters":[{"name":"id","in":"path","required":true,"schema":{"type":"string"}}],"responses":{"204":{"content":{"application/json":{"schema":{"type":"object"}}}}}}},"/schema/subscription/search":{"post":{"summary":"Fetch multiple Subscription","description":"Fetch multiple Subscription from database","tags":["schema.subscription.search"],"operationId":"Fetch_multiple Subscription","requestBody":{"content":{"application/json":{"schema":{"type":"object"}}}},"responses":{"200":{"content":{"application/json":{"schema":{"type":"array"}}}}}}},"/schema/user":{"post":{"summary":"Create a new User","description":"Create User from database","tags":["schema.user.create"],"operationId":"Create_a new User","requestBody":{"content":{"application/json":{"schema":{"$ref":"#/components/schemas/schema_User"}}}},"responses":{"201":{"content":{"application/json":{"schema":{"type":"object"}}}}}}},"/schema/user/{id}":{"delete":{"summary":"Delete a User","description":"Delete User from database","tags":["schema.user.delete"],"operationId":"Delete_a User","parameters":[{"name":"id","in":"path","required":true,"schema":{"type":"string"}}],"responses":{"202":{"content":{"application/json":{"schema":{"type":"object"}}}}}},"get":{"summary":"Fetch User","description":"Fetch User from database","tags":["schema.user.one"],"operationId":"Fetch_User","parameters":[{"name":"id","in":"path","required":true,"schema":{"type":"string"}}],"responses":{"200":{"content":{"application/json":{"schema":{"type":"object"}}}}}},"put":{"summary":"Update a User","description":"Update User from database","tags":["schema.user.update"],"operationId":"Update_a User","requestBody":{"content":{"application/json":{"schema":{"$ref":"#/components/schemas/schema_User"}}}},"parameters":[{"name":"id","in":"path","required":true,"schema":{"type":"string"}}],"responses":{"204":{"content":{"application/json":{"schema":{"type":"object"}}}}}}},"/schema/user/search":{"post":{"summary":"Fetch multiple User","description":"Fetch multiple User from database","tags":["schema.user.search"],"operationId":"Fetch_multiple User","requestBody":{"content":{"application/json":{"schema":{"type":"object"}}}},"responses":{"200":{"content":{"application/json":{"schema":{"type":"array"}}}}}}}},"servers":[{"url":"http://localhost:3000","description":"Public API server"},{"url":"http://localhost:3001","description":"Internal API server"}],"info":{"title":"Sample Helloworld App","version":"1.1.0","summary":"Some http calls","description":"Lets play with Godspeed","contact":{"name":"API Support","url":"http://www.helloworld.com/support","email":"support@helloworld.com"},"license":{"name":"Apache 2.0","url":"https://www.apache.org/licenses/LICENSE-2.0.html"}},"components":{"schemas":{"schema_Company":{"type":"object","properties":{"name":{"type":"string"}}},"schema_Product":{"type":"object","properties":{"name":{"type":"string"},"description":{"type":"string","nullable":true},"companyId":{"type":"string"}}},"schema_Package":{"type":"object","properties":{"name":{"type":"string"},"productId":{"type":"string"}}},"schema_Subscription":{"type":"object","properties":{"userId":{"type":"string"},"packageId":{"type":"string"},"active":{"type":"boolean","default":true},"startDate":{"type":"string","format":"date-time"},"endDate":{"type":"string","format":"date-time","nullable":true}}},"schema_User":{"type":"object","properties":{"email":{"type":"string"},"role":{"type":"string","enum":["ADMIN","USER"]},"companyId":{"type":"string"}}}}}}